python_myspeed/VERSION
python_myspeed/__init__.py
python_myspeed/_version.py
python_myspeed/core.py
python_myspeed/exceptions.py
python_myspeed/models.py
python_myspeed-0.1.0.dist-info/LICENSE
python_myspeed-0.1.0.dist-info/METADATA
python_myspeed-0.1.0.dist-info/WHEEL
python_myspeed-0.1.0.dist-info/RECORD
