Metadata-Version: 2.1
Name: python-myspeed
Version: 0.1.0
Summary: A python wrapper for the MySpeed API.
Home-page: https://github.com/jkrgr0/python-myspeed
Author: jkrgr0
Requires-Python: >=3.11,<4.0
Classifier: Programming Language :: Python :: 3
Classifier: Programming Language :: Python :: 3.11
Classifier: Programming Language :: Python :: 3.12
Requires-Dist: requests (>=2.32.3,<3.0.0)
Project-URL: Repository, https://github.com/jkrgr0/python-myspeed
